odoo/addons/sale_stock_operating_unit/README.rst
odoo/addons/sale_stock_operating_unit/__init__.py
odoo/addons/sale_stock_operating_unit/__manifest__.py
odoo/addons/sale_stock_operating_unit/i18n/it.po
odoo/addons/sale_stock_operating_unit/i18n/pt.po
odoo/addons/sale_stock_operating_unit/i18n/sale_stock_operating_unit.pot
odoo/addons/sale_stock_operating_unit/models/__init__.py
odoo/addons/sale_stock_operating_unit/models/sale_order.py
odoo/addons/sale_stock_operating_unit/models/stock_move.py
odoo/addons/sale_stock_operating_unit/models/stock_warehouse.py
odoo/addons/sale_stock_operating_unit/readme/CONFIGURATION.rst
odoo/addons/sale_stock_operating_unit/readme/CONTRIBUTORS.md
odoo/addons/sale_stock_operating_unit/readme/DESCRIPTION.md
odoo/addons/sale_stock_operating_unit/readme/USAGE.md
odoo/addons/sale_stock_operating_unit/static/description/icon.png
odoo/addons/sale_stock_operating_unit/static/description/index.html
odoo/addons/sale_stock_operating_unit/tests/__init__.py
odoo/addons/sale_stock_operating_unit/tests/test_sale_stock_operating_unit.py
odoo_addon_sale_stock_operating_unit-18.0.1.0.0.2.dist-info/METADATA
odoo_addon_sale_stock_operating_unit-18.0.1.0.0.2.dist-info/WHEEL
odoo_addon_sale_stock_operating_unit-18.0.1.0.0.2.dist-info/top_level.txt
odoo_addon_sale_stock_operating_unit-18.0.1.0.0.2.dist-info/RECORD
